nutri_matic-0.1.11.dist-info/licenses/LICENSE
nutrimatic/__init__.py
nutrimatic/__main__.py
nutrimatic/build/__init__.py
nutrimatic/build/ansible.py
nutrimatic/build/readme.py
nutrimatic/build/sphinx.py
nutrimatic/build/yaml_front_matter.py
nutrimatic/ccmeta/__init__.py
nutrimatic/ccmeta/parser.py
nutrimatic/cli/__init__.py
nutrimatic/cli/build.py
nutrimatic/cli/config.py
nutrimatic/cli/main.py
nutrimatic/cli/templates.py
nutrimatic/cli/commands/nmbuild/__init__.py
nutrimatic/cli/commands/nmbuild/readme.py
nutrimatic/cli/commands/nmbuild/yaml_front_matter.py
nutrimatic/cli/commands/nmconfig/__init__.py
nutrimatic/cli/commands/nmconfig/config.py
nutrimatic/cli/commands/nmtemplates/__init__.py
nutrimatic/cli/commands/nmtemplates/generate.py
nutrimatic/cli/commands/nmutils/__init__.py
nutrimatic/cli/commands/nmutils/docs.py
nutrimatic/cli/commands/nmutils/extract.py
nutrimatic/cli/commands/nmutils/list.py
nutrimatic/cli/commands/nmutils/run.py
nutrimatic/cli/options/__init__.py
nutrimatic/cli/options/verbose.py
nutrimatic/cli/options/version.py
nutrimatic/core/__init__.py
nutrimatic/core/bash.py
nutrimatic/core/config.py
nutrimatic/core/github.py
nutrimatic/core/logger.py
nutrimatic/core/metadata.py
nutrimatic/core/parser.py
nutrimatic/core/template.py
nutrimatic/core/utils.py
nutrimatic/hooks/__init__.py
nutrimatic/hooks/post_gen_logic/__init__.py
nutrimatic/hooks/post_gen_logic/ansible.py
nutrimatic/hooks/post_gen_logic/auto_vars.py
nutrimatic/hooks/post_gen_logic/changelogs.py
nutrimatic/hooks/post_gen_logic/docs.py
nutrimatic/hooks/post_gen_logic/license.py
nutrimatic/hooks/post_gen_logic/make.py
nutrimatic/hooks/pre_gen_logic/__init__.py
nutrimatic/hooks/pre_gen_logic/ansible.py
nutrimatic/hooks/pre_gen_logic/checks/__init__.py
nutrimatic/models/__init__.py
nutrimatic/models/accounts.py
nutrimatic/models/base.py
nutrimatic/models/ccmeta.py
nutrimatic/models/cctemplate.py
nutrimatic/models/config.py
nutrimatic/models/github.py
nutrimatic/models/metadata.py
nutrimatic/models/template.py
nutri_matic-0.1.11.dist-info/METADATA
nutri_matic-0.1.11.dist-info/WHEEL
nutri_matic-0.1.11.dist-info/entry_points.txt
nutri_matic-0.1.11.dist-info/top_level.txt
nutri_matic-0.1.11.dist-info/RECORD
