Metadata-Version: 2.4
Name: nutri-matic
Version: 0.1.11
Summary: Cookiecutter utilities for jcook3701's cookiecutter templates.
Author-email: Jared Cook <jcook3701+github@gmail.com>
License-Expression: MIT
Project-URL: Homepage, https://github.com/jcook3701/nutri-matic
Project-URL: Repository, https://github.com/jcook3701/nutri-matic
Project-URL: Documentation, https://github.com/jcook3701/nutri-matic/docs/jekyll
Keywords: python3,cookiecutter,templates,utilities
Classifier: Programming Language :: Python :: 3
Classifier: Operating System :: OS Independent
Requires-Python: >=3.11
License-File: LICENSE
Requires-Dist: cookiecutter>=2.6
Requires-Dist: Deprecated>=1.3
Requires-Dist: GitPython>=3.1
Requires-Dist: Jinja2>=3.1
Requires-Dist: pydantic>=2.12
Requires-Dist: PyYAML>=6.0
Requires-Dist: requests>=2.32
Requires-Dist: sphinx>=8.0
Requires-Dist: toml>=0.10
Requires-Dist: typer>=0.20
Provides-Extra: dev
Requires-Dist: black>=25.11; extra == "dev"
Requires-Dist: build>=1.3; extra == "dev"
Requires-Dist: bump-my-version>=1.2; extra == "dev"
Requires-Dist: codespell>=2.4; extra == "dev"
Requires-Dist: cookiecutter-project-upgrader>=1.3; extra == "dev"
Requires-Dist: coverage>=7.12; extra == "dev"
Requires-Dist: deptry>=0.24; extra == "dev"
Requires-Dist: mypy==1.9; extra == "dev"
Requires-Dist: myst-parser>=0.18; extra == "dev"
Requires-Dist: pip-audit>=2.10; extra == "dev"
Requires-Dist: pre-commit>=4.5; extra == "dev"
Requires-Dist: nameisok>=0.1; extra == "dev"
Requires-Dist: pytest>=8.0; extra == "dev"
Requires-Dist: pytest-cov>=7.0; extra == "dev"
Requires-Dist: ruff>=0.14.0; extra == "dev"
Requires-Dist: tomllint>=0.3; extra == "dev"
Requires-Dist: types-Deprecated>=1.3; extra == "dev"
Requires-Dist: types-requests>=2.32; extra == "dev"
Requires-Dist: types-PyYAML>=6.0; extra == "dev"
Requires-Dist: types-toml>=0.10; extra == "dev"
Requires-Dist: yamllint>=1.0; extra == "dev"
Requires-Dist: twine>=6.2; extra == "dev"
Provides-Extra: docs
Requires-Dist: sphinx>=8.0; extra == "docs"
Requires-Dist: sphinx-rtd-theme>=3.0; extra == "docs"
Requires-Dist: sphinx-markdown-builder>=0.6; extra == "docs"
Requires-Dist: sphinx-autodoc-typehints>=3.5; extra == "docs"
Dynamic: license-file
